truecase/Trainer.py
truecase/TrueCaser.py
truecase/__init__.py
truecase/data/english.dist
truecase-0.0.14.dist-info/LICENSE
truecase-0.0.14.dist-info/METADATA
truecase-0.0.14.dist-info/WHEEL
truecase-0.0.14.dist-info/top_level.txt
truecase-0.0.14.dist-info/RECORD
